helicone_prompts/__init__.py
helicone_prompts/auto_fill.py
helicone_prompts/object_parser.py
helicone_prompts/object_version_checking.py
helicone_prompts/prompts.py
helicone_prompts/tests/__init__.py
helicone_prompts/tests/test_auto_fill.py
helicone_prompts/tests/test_object_parser.py
helicone_prompts/tests/test_object_version_checking.py
helicone_prompts/tests/test_prompts.py
helicone_prompts-0.0.1.dist-info/METADATA
helicone_prompts-0.0.1.dist-info/WHEEL
helicone_prompts-0.0.1.dist-info/RECORD
